midap/__init__.py
midap/checkpoint.py
midap/config.py
midap/main.py
midap/main_family_machine.py
midap/main_mother_machine.py
midap/run_benchmark.py
midap/utils.py
midap/apps/PySimpleGUI.py
midap/apps/__init__.py
midap/apps/analyse_tracking.py
midap/apps/correct_segmentation.py
midap/apps/cut_chamber.py
midap/apps/download_files.py
midap/apps/download_info.json
midap/apps/init_GUI.py
midap/apps/seg_fluo_change_analysis.py
midap/apps/segment_analysis.py
midap/apps/segment_cells.py
midap/apps/split_frames.py
midap/apps/track_analysis.py
midap/apps/track_cells.py
midap/correction/__init__.py
midap/correction/napari_correction.py
midap/data/__init__.py
midap/data/preprocessing.py
midap/data/tf_pipeline.py
midap/imcut/__init__.py
midap/imcut/base_cutout.py
midap/imcut/interactive_cutout.py
midap/imcut/semiautomated_cutout.py
midap/midap_jupyter/__init__.py
midap/midap_jupyter/segmentation_jupyter.py
midap/networks/__init__.py
midap/networks/deltav1.py
midap/networks/deltav2.py
midap/networks/layers.py
midap/networks/unets.py
midap/networks/evaluation/__init__.py
midap/networks/evaluation/evaluation.py
midap/networks/evaluation/metrics.py
midap/networks/evaluation/tf_metrics.py
midap/segmentation/__init__.py
midap/segmentation/base_segmentator.py
midap/segmentation/hybrid_segmentator.py
midap/segmentation/omni_segmentator.py
midap/segmentation/omni_segmentator_jupyter.py
midap/segmentation/stardist_segmentator.py
midap/segmentation/stardist_segmentator_jupyter.py
midap/segmentation/unet_segmentator.py
midap/segmentation/unet_segmentator_jupyter.py
midap/tracking/__init__.py
midap/tracking/base_tracking.py
midap/tracking/bayesian_tracking.py
midap/tracking/btrack_conf.json
midap/tracking/cell_props.py
midap/tracking/delta_lineage.py
midap/tracking/deltav1_tracking.py
midap/tracking/deltav2_tracking.py
midap/tracking/strack_lineages.py
midap/tracking/strack_tracking.py
midap/tracking/tracking_analysis.py
midap/tracking/strack/__init__.py
midap-1.0.1.dist-info/LICENSE
midap-1.0.1.dist-info/LICENSE.txt
midap-1.0.1.dist-info/METADATA
midap-1.0.1.dist-info/WHEEL
midap-1.0.1.dist-info/entry_points.txt
midap-1.0.1.dist-info/top_level.txt
midap-1.0.1.dist-info/RECORD
