Metadata-Version: 2.1
Name: midap
Version: 1.0.1
Summary: A package for cell segmentation and tracking.
Download-URL: https://github.com/Microbial-Systems-Ecology/midap/releases/tag/0.3.18
Author: Oschmann  Franziska, Fluri Janis
Author-email: franziska.oschmann@id.ethz.ch, janis.fluri@id.ethz.ch
Project-URL: Midap, https://gitlab.ethz.ch/oschmanf/ackermann-bacteria-segmentation/
Keywords: Segmentation,Tracking,Biology
Requires-Python: >=3.9, <4
License-File: LICENSE
License-File: LICENSE.txt
Requires-Dist: btrack==0.4.6
Requires-Dist: coverage>=7.3.2
Requires-Dist: gitpython>=3.1.40
Requires-Dist: jupyterlab==4.0.8
Requires-Dist: matplotlib<=3.6.3,>=3.3.0
Requires-Dist: napari[all]
Requires-Dist: omnipose==0.4.4
Requires-Dist: opencv-python>=4.8.1
Requires-Dist: pandas>=2.0.2
Requires-Dist: psutil>=5.9.0
Requires-Dist: pytest>=7.4.3
Requires-Dist: scikit-image<=0.20.0,>=0.19.3
Requires-Dist: stardist>=0.8.5
Requires-Dist: tensorflow==2.13.0
Requires-Dist: tqdm>=4.65.0
Requires-Dist: build
Requires-Dist: twine
Requires-Dist: tensorflow-metal
